LICENSE
README.md
setup.py
novotools/__init__.py
novotools.egg-info/PKG-INFO
novotools.egg-info/SOURCES.txt
novotools.egg-info/dependency_links.txt
novotools.egg-info/requires.txt
novotools.egg-info/top_level.txt
novotools/tools/excel2text.py
novotools/tools/getcol.py
novotools/tools/text2excel.py
novotools/tools/__init__.py
novotools/tools/excel2text.py
novotools/tools/getcol.py
novotools/tools/text2excel.py
novotools/utils/__init__.py
novotools/utils/email_opt.py
novotools/utils/logging_opt.py
novotools/utils/process_and_thread.py
novotools/utils/string_format_and_file_opt.py
novotools/utils/time_opt.py
test/test.py